[
    {
        "id": "7e3f538b0a501e41",
        "type": "tab",
        "label": "Flujo 3",
        "disabled": false,
        "info": "",
        "env": []
    },
    {
        "id": "0a7a86533427c846",
        "type": "kafkajs-producer",
        "z": "7e3f538b0a501e41",
        "name": "",
        "client": "89e380a1c824ddad",
        "topic": "prueba",
        "advancedoptions": true,
        "acknowledge": "none",
        "partition": "",
        "headeritems": {},
        "key": "",
        "responsetimeout": 30000,
        "transactiontimeout": 60000,
        "metadatamaxage": 300000,
        "allowautotopiccreation": false,
        "x": 840,
        "y": 300,
        "wires": []
    },
    {
        "id": "907275f80616f5ce",
        "type": "kafkajs-consumer",
        "z": "7e3f538b0a501e41",
        "name": "",
        "client": "89e380a1c824ddad",
        "groupid": "",
        "topic": "prueba",
        "advancedoptions": false,
        "autocommitinterval": 5000,
        "autocommitthreshold": 100,
        "sessiontimeout": 30000,
        "rebalancetimeout": 60000,
        "heartbeatinterval": 3000,
        "metadatamaxage": 300000,
        "maxbytesperpartition": 1048576,
        "minbytes": 1,
        "maxbytes": 10485760,
        "maxwaittimeinms": 5000,
        "frombeginning": false,
        "clearoffsets": false,
        "allowautotopiccreation": false,
        "x": 600,
        "y": 360,
        "wires": [
            [
                "ee85ea067fbcd61e"
            ]
        ]
    },
    {
        "id": "070d3019bd46238b",
        "type": "inject",
        "z": "7e3f538b0a501e41",
        "name": "",
        "props": [
            {
                "p": "payload"
            },
            {
                "p": "topic",
                "vt": "str"
            }
        ],
        "repeat": "",
        "crontab": "",
        "once": false,
        "onceDelay": 0.1,
        "topic": "",
        "payload": "",
        "payloadType": "date",
        "x": 530,
        "y": 300,
        "wires": [
            [
                "5d87b663fe67c9e2"
            ]
        ]
    },
    {
        "id": "ee85ea067fbcd61e",
        "type": "debug",
        "z": "7e3f538b0a501e41",
        "name": "debug 5",
        "active": true,
        "tosidebar": true,
        "console": false,
        "tostatus": false,
        "complete": "payload",
        "targetType": "msg",
        "statusVal": "",
        "statusType": "auto",
        "x": 760,
        "y": 360,
        "wires": []
    },
    {
        "id": "5d87b663fe67c9e2",
        "type": "function",
        "z": "7e3f538b0a501e41",
        "name": "function 2",
        "func": "let json_content = { texto: \"Hola Mundo!\" }\nmsg.payload = JSON.stringify(json_content);\nreturn msg;\n",
        "outputs": 1,
        "timeout": 0,
        "noerr": 0,
        "initialize": "",
        "finalize": "",
        "libs": [],
        "x": 680,
        "y": 300,
        "wires": [
            [
                "0a7a86533427c846"
            ]
        ]
    },
    {
        "id": "89e380a1c824ddad",
        "type": "kafkajs-client",
        "name": "octo-kafka",
        "brokers": "kafka:9092",
        "clientid": "nodered-producer",
        "connectiontimeout": 3000,
        "requesttimeout": 25000,
        "advancedretry": false,
        "maxretrytime": 30000,
        "initialretrytime": 300,
        "factor": 0.2,
        "multiplier": 2,
        "retries": 5,
        "auth": "none",
        "tlsselfsign": false,
        "tlscacert": "",
        "tlsclientcert": "",
        "tlsprivatekey": "",
        "tlspassphrase": "",
        "saslssl": true,
        "saslmechanism": "plain",
        "loglevel": "error"
    }
]